ae/event_detector.doctest.rst
ae/__init__.py
ae/test.py
ae/ae.py
ae/event_detector.pyd
ae/version.py
ae/askc_wrap.py
ae-0.2.83.data/scripts/ae_post_install.py
ae-0.2.83.data/scripts/AEViewer.ico
ae-0.2.83.data/scripts/AEViewer.py
ae-0.2.83.dist-info/RECORD
ae-0.2.83.dist-info/WHEEL
ae-0.2.83.dist-info/DESCRIPTION.rst
ae-0.2.83.dist-info/metadata.json
ae-0.2.83.dist-info/METADATA
ae-0.2.83.dist-info/top_level.txt
