Metadata-Version: 1.0
Name: ae
Version: 0.2.83
Summary: Python accoustic emission tools
Home-page: http://github.com/jove1/ae
Author: Jozef Vesely
Author-email: vesely@gjh.sk
License: UNKNOWN
Platform: UNKNOWN
